msgen_cli/__init__.py
msgen_cli/datatransfer.py
msgen_cli/malibuargs.py
msgen_cli/malibuargsactions.py
msgen_cli/malibuazure.py
msgen_cli/malibucommon.py
msgen_cli/malibuservice.py
msgen_cli/malibuworkflow.py
msgen_cli/msgen.py
msgen-0.9.1.dist-info/LICENSE.rst
msgen-0.9.1.dist-info/LICENSE.txt
msgen-0.9.1.dist-info/METADATA
msgen-0.9.1.dist-info/WHEEL
msgen-0.9.1.dist-info/entry_points.txt
msgen-0.9.1.dist-info/top_level.txt
msgen-0.9.1.dist-info/RECORD
