Metadata-Version: 2.1
Name: msgen
Version: 0.9.1
Summary: Microsoft Genomics Command-line Client
Home-page: https://github.com/microsoft/msgen
Author: Microsoft Corporation, Microsoft Genomics Team
Author-email: msgensupp@microsoft.com
License: MIT
Keywords: azure genomics
Platform: any
Classifier: Environment :: Console
Classifier: License :: OSI Approved :: MIT License
Classifier: Operating System :: OS Independent
Classifier: Programming Language :: Python :: 2
Classifier: Programming Language :: Python :: 2.7
Requires-Dist: azure-storage (==0.32.0)
Requires-Dist: requests (>=2.11.1)
